tests/__init__.py
tests/test_basic.py
tests/test_parse_address.py
vn_address_converter/__init__.py
vn_address_converter/aliases.py
vn_address_converter/converter.py
vn_address_converter/mapping.py
vn_address_converter/models.py
vn_address_converter/parser.py
vn_address_converter/data/manual_aliases.json
vn_address_converter/data/ward_mapping.json
vn_address_converter-0.1.3.dist-info/licenses/LICENSE
vn_address_converter-0.1.3.dist-info/METADATA
vn_address_converter-0.1.3.dist-info/WHEEL
vn_address_converter-0.1.3.dist-info/top_level.txt
vn_address_converter-0.1.3.dist-info/RECORD
