Metadata-Version: 2.4
Name: vn-address-converter
Version: 0.1.3
Summary: A Python package for converting and normalizing Vietnamese addresses
Home-page: https://github.com/nqbao/vn-address-converter
Author: Bao Nguyen
Author-email: Bao Nguyen <qbao.nguyen@gmail.com>
License: MIT
Project-URL: Homepage, https://github.com/nqbao/vn-address-converter
Project-URL: Repository, https://github.com/nqbao/vn-address-converter
Project-URL: Issues, https://github.com/nqbao/vn-address-converter/issues
Classifier: Development Status :: 3 - Alpha
Classifier: Intended Audience :: Developers
Classifier: License :: OSI Approved :: MIT License
Classifier: Operating System :: OS Independent
Classifier: Programming Language :: Python :: 3
Classifier: Programming Language :: Python :: 3.10
Classifier: Programming Language :: Python :: 3.11
Classifier: Programming Language :: Python :: 3.12
Requires-Python: >=3.10
License-File: LICENSE
Provides-Extra: dev
Requires-Dist: pytest; extra == "dev"
Requires-Dist: black; extra == "dev"
Requires-Dist: flake8; extra == "dev"
Requires-Dist: mypy; extra == "dev"
Requires-Dist: build; extra == "dev"
Dynamic: author
Dynamic: home-page
Dynamic: license-file
Dynamic: requires-python
